mprisctl.py
mprisctl-0.0.1.dist-info/LICENSE
mprisctl-0.0.1.dist-info/METADATA
mprisctl-0.0.1.dist-info/WHEEL
mprisctl-0.0.1.dist-info/entry_points.txt
mprisctl-0.0.1.dist-info/top_level.txt
mprisctl-0.0.1.dist-info/RECORD
