Metadata-Version: 2.1
Name: mprisctl
Version: 0.0.1
Summary: Command line utility to control music players.
Home-page: https://github.com/RangHo/mprisctl
Author: RangHo Lee
Author-email: RangHo Lee <hello@rangho.me>
Project-URL: Homepage, https://github.com/RangHo/mprisctl
Project-URL: Bug Tracker, https://github.com/RangHo/mprisctl/issues
Classifier: Programming Language :: Python :: 3
Classifier: License :: OSI Approved :: MIT License
Classifier: Operating System :: POSIX
Requires-Python: >=3.7
License-File: LICENSE
